moviegraphbenchmark/__init__.py
moviegraphbenchmark/create_graph.py
moviegraphbenchmark/get_imdb_data.py
moviegraphbenchmark/loading.py
moviegraphbenchmark/utils.py
moviegraphbenchmark-1.1.0.dist-info/entry_points.txt
moviegraphbenchmark-1.1.0.dist-info/WHEEL
moviegraphbenchmark-1.1.0.dist-info/METADATA
moviegraphbenchmark-1.1.0.dist-info/RECORD
