Metadata-Version: 2.1
Name: moviegraphbenchmark
Version: 1.1.0
Summary: Benchmark datasets for Entity Resolution on Knowledge Graphs containing information about movies, tv shows and persons from IMDB,TMDB and TheTVDB
Home-page: https://github.com/ScaDS/MovieGraphBenchmark
Author: Daniel Obraczka
Author-email: obraczka@informatik.uni-leipzig.de
Requires-Python: >=3.8
Classifier: Programming Language :: Python :: 3
Classifier: Programming Language :: Python :: 3.8
Classifier: Programming Language :: Python :: 3.9
Classifier: Programming Language :: Python :: 3.10
Classifier: Programming Language :: Python :: 3.11
Requires-Dist: pandas
Requires-Dist: pystow
Requires-Dist: requests
Requires-Dist: tqdm
Project-URL: Repository, https://github.com/ScaDS/MovieGraphBenchmark
